lektor_minify_html.py
lektor_minify_html-0.2.0.dist-info/LICENSE
lektor_minify_html-0.2.0.dist-info/METADATA
lektor_minify_html-0.2.0.dist-info/WHEEL
lektor_minify_html-0.2.0.dist-info/entry_points.txt
lektor_minify_html-0.2.0.dist-info/top_level.txt
lektor_minify_html-0.2.0.dist-info/RECORD
