Metadata-Version: 2.1
Name: lektor-minify-html
Version: 0.2.0
Summary: Minify content using minify-html
Author: seralot
License: MIT License
Project-URL: Repository, https://github.com/seralot/lektor-minify-html/
Project-URL: Issues, https://github.com/seralot/lektor-minify-html/issues
License-File: LICENSE
Requires-Dist: minify-html
